odoo/addons/l10n_ch_pain_base/README.rst
odoo/addons/l10n_ch_pain_base/__init__.py
odoo/addons/l10n_ch_pain_base/__manifest__.py
odoo/addons/l10n_ch_pain_base/i18n/de.po
odoo/addons/l10n_ch_pain_base/i18n/fr.po
odoo/addons/l10n_ch_pain_base/i18n/it.po
odoo/addons/l10n_ch_pain_base/i18n/l10n_ch_pain_base.pot
odoo/addons/l10n_ch_pain_base/models/__init__.py
odoo/addons/l10n_ch_pain_base/models/account_move_line.py
odoo/addons/l10n_ch_pain_base/models/account_payment_line.py
odoo/addons/l10n_ch_pain_base/models/account_payment_order.py
odoo/addons/l10n_ch_pain_base/readme/CONTRIBUTORS.rst
odoo/addons/l10n_ch_pain_base/readme/DESCRIPTION.rst
odoo/addons/l10n_ch_pain_base/static/description/icon.png
odoo/addons/l10n_ch_pain_base/static/description/index.html
odoo/addons/l10n_ch_pain_base/views/account_payment_line.xml
odoo14_addon_l10n_ch_pain_base-14.0.1.0.1.dev4.dist-info/METADATA
odoo14_addon_l10n_ch_pain_base-14.0.1.0.1.dev4.dist-info/WHEEL
odoo14_addon_l10n_ch_pain_base-14.0.1.0.1.dev4.dist-info/top_level.txt
odoo14_addon_l10n_ch_pain_base-14.0.1.0.1.dev4.dist-info/RECORD
